lazyscience/__init__.py
lazyscience/debug.py
lazyscience/lazyscience.py
lazyscience-0.0.2.dist-info/LICENSE
lazyscience-0.0.2.dist-info/METADATA
lazyscience-0.0.2.dist-info/WHEEL
lazyscience-0.0.2.dist-info/top_level.txt
lazyscience-0.0.2.dist-info/RECORD
